Streamlit_menu/__init__.py
Streamlit_menu/multipage.py
Streamlit_menu/st_menu/__init__.py
Streamlit_menu/st_menu/register.py
streamlit_menu_component-1.0.0.dist-info/METADATA
streamlit_menu_component-1.0.0.dist-info/WHEEL
streamlit_menu_component-1.0.0.dist-info/top_level.txt
streamlit_menu_component-1.0.0.dist-info/RECORD
