Metadata-Version: 2.1
Name: streamlit-menu-component
Version: 1.0.0
Summary: Customizable menu component for the streamlit developes
Home-page: 
Author: Subhash Jadhav
Author-email: subhash.jadhav@bluepineapple.io
Requires-Python: >=3.6
Requires-Dist: streamlit (>=1.15.1)
